odoo/addons/mail_autogenerated_header/README.rst
odoo/addons/mail_autogenerated_header/__init__.py
odoo/addons/mail_autogenerated_header/__manifest__.py
odoo/addons/mail_autogenerated_header/i18n/mail_autogenerated_header.pot
odoo/addons/mail_autogenerated_header/models/__init__.py
odoo/addons/mail_autogenerated_header/models/ir_mail_server.py
odoo/addons/mail_autogenerated_header/models/mail_thread.py
odoo/addons/mail_autogenerated_header/models/res_partner.py
odoo/addons/mail_autogenerated_header/readme/CONTRIBUTORS.rst
odoo/addons/mail_autogenerated_header/readme/DESCRIPTION.rst
odoo/addons/mail_autogenerated_header/readme/USAGE.rst
odoo/addons/mail_autogenerated_header/readme/newsfragments/.gitkeep
odoo/addons/mail_autogenerated_header/static/description/icon.png
odoo/addons/mail_autogenerated_header/static/description/index.html
odoo/addons/mail_autogenerated_header/tests/__init__.py
odoo/addons/mail_autogenerated_header/tests/test_mail_autogenerated_header.py
odoo12_addon_mail_autogenerated_header-12.0.1.0.0.99.dev4.dist-info/METADATA
odoo12_addon_mail_autogenerated_header-12.0.1.0.0.99.dev4.dist-info/WHEEL
odoo12_addon_mail_autogenerated_header-12.0.1.0.0.99.dev4.dist-info/top_level.txt
odoo12_addon_mail_autogenerated_header-12.0.1.0.0.99.dev4.dist-info/RECORD
