Metadata-Version: 2.1
Name: odoo12-addon-mail-autogenerated-header
Version: 12.0.1.0.0.99.dev4
Summary: Add headers to Odoo's mails indicating they are autogenerated
Home-page: https://github.com/OCA/social
Author: Hunki Enterprises BV, Therp BV,Odoo Community Association (OCA)
Author-email: support@odoo-community.org
License: AGPL-3
Platform: UNKNOWN
Classifier: Programming Language :: Python
Classifier: Framework :: Odoo
Classifier: Framework :: Odoo :: 12.0
Classifier: License :: OSI Approved :: GNU Affero General Public License v3
Requires-Python: >=3.5
Requires-Dist: odoo <12.1dev,>=12.0a
